tooler/__init__.py
tooler/command.py
tooler/exceptions.py
tooler/output.py
tooler/parser.py
tooler/tooler.py
tooler/version.py
tooler/clide/ansi.py
tooler/clide/english.py
tooler-0.1.5rc1.dist-info/METADATA
tooler-0.1.5rc1.dist-info/WHEEL
tooler-0.1.5rc1.dist-info/entry_points.txt
tooler-0.1.5rc1.dist-info/licenses/LICENSE
tooler-0.1.5rc1.dist-info/RECORD
